LICENSE.txt
MANIFEST.in
README.rst
setup.py
django_quotidian.egg-info/PKG-INFO
django_quotidian.egg-info/SOURCES.txt
django_quotidian.egg-info/dependency_links.txt
django_quotidian.egg-info/not-zip-safe
django_quotidian.egg-info/top_level.txt
quotidian/__init__.py
quotidian/admin.py
quotidian/context_processors.py
quotidian/models.py
quotidian/tests.py